pypasslib/__init__.py
pypasslib/main.py
pypasslib-1.1.dist-info/LICENSE.txt
pypasslib-1.1.dist-info/METADATA
pypasslib-1.1.dist-info/WHEEL
pypasslib-1.1.dist-info/top_level.txt
pypasslib-1.1.dist-info/RECORD
