Metadata-Version: 2.1
Name: pypasslib
Version: 1.1
Summary: A Python module containing a list of a million passwords to use for educational purposes only
Home-page: https://github.com/Opticz45/pypasslib
Author: Opticz
Author-email: cartiscott45@gmail.com
Classifier: Programming Language :: Python :: 3
Classifier: Operating System :: OS Independent
Requires-Python: >=3.6
License-File: LICENSE.txt
